odoo/addons/shopinvader_product_stock_state/README.rst
odoo/addons/shopinvader_product_stock_state/__init__.py
odoo/addons/shopinvader_product_stock_state/__manifest__.py
odoo/addons/shopinvader_product_stock_state/models/__init__.py
odoo/addons/shopinvader_product_stock_state/models/shopinvader_backend.py
odoo/addons/shopinvader_product_stock_state/models/shopinvader_variant.py
odoo/addons/shopinvader_product_stock_state/readme/CONTRIBUTORS.rst
odoo/addons/shopinvader_product_stock_state/readme/CREDITS.rst
odoo/addons/shopinvader_product_stock_state/readme/DESCRIPTION.rst
odoo/addons/shopinvader_product_stock_state/readme/USAGE.rst
odoo/addons/shopinvader_product_stock_state/static/description/index.html
odoo/addons/shopinvader_product_stock_state/tests/__init__.py
odoo/addons/shopinvader_product_stock_state/tests/test_product.py
odoo/addons/shopinvader_product_stock_state/views/shopinvader_backend.xml
odoo12_addon_shopinvader_product_stock_state-12.0.1.0.1.dist-info/METADATA
odoo12_addon_shopinvader_product_stock_state-12.0.1.0.1.dist-info/WHEEL
odoo12_addon_shopinvader_product_stock_state-12.0.1.0.1.dist-info/top_level.txt
odoo12_addon_shopinvader_product_stock_state-12.0.1.0.1.dist-info/RECORD
